whampy/__init__.py
whampy/_astropy_init.py
whampy/clickMap.py
whampy/conftest.py
whampy/dataReduction.py
whampy/lbvTracks.py
whampy/scaleHeight.py
whampy/skySurvey.py
whampy/spectralStack.py
whampy/version.py
whampy/whampyTableMixin.py
whampy/data/README.rst
whampy/data/wham-ss-DR1-v161116-170912.fits
whampy/data/Reid16_SpiralArms/3kF_lbvRBD.dat
whampy/data/Reid16_SpiralArms/3kN_lbvRBD.dat
whampy/data/Reid16_SpiralArms/AqR_lbvRBD.dat
whampy/data/Reid16_SpiralArms/AqS_lbvRBD.dat
whampy/data/Reid16_SpiralArms/CnN_lbvRBD.dat
whampy/data/Reid16_SpiralArms/CnX_lbvRBD.dat
whampy/data/Reid16_SpiralArms/CrF_lbvRBD.dat
whampy/data/Reid16_SpiralArms/CrN_lbvRBD.dat
whampy/data/Reid16_SpiralArms/CtF_lbvRBD.dat
whampy/data/Reid16_SpiralArms/CtN_lbvRBD.dat
whampy/data/Reid16_SpiralArms/LoS_lbvRBD.dat
whampy/data/Reid16_SpiralArms/Loc_lbvRBD.dat
whampy/data/Reid16_SpiralArms/Nor_lbvRBD.dat
whampy/data/Reid16_SpiralArms/OSC_lbvRBD.dat
whampy/data/Reid16_SpiralArms/Out_lbvRBD.dat
whampy/data/Reid16_SpiralArms/Per_lbvRBD.dat
whampy/data/Reid16_SpiralArms/ScF_lbvRBD.dat
whampy/data/Reid16_SpiralArms/ScN_lbvRBD.dat
whampy/data/Reid16_SpiralArms/SgF_lbvRBD.dat
whampy/data/Reid16_SpiralArms/SgN_lbvRBD.dat
whampy/extern/__init__.py
whampy/tests/__init__.py
whampy/tests/setup_package.py
whampy/tests/test_click_map.py
whampy/tests/test_equivalent_width.py
whampy/tests/test_fit_scale_height.py
whampy/tests/test_get_scale_height_data.py
whampy/tests/test_get_spectrum.py
whampy/tests/test_intensity_maps.py
whampy/tests/test_lbv_tracks.py
whampy/tests/test_load_SkySurvey.py
whampy/tests/test_moments.py
whampy/tests/test_over_data_click_map.py
whampy/tests/test_spectral_slab.py
whampy/tests/test_spectral_stack.py
whampy/tests/test_transmissions.py
whampy/tests/test_tuner.py
whampy/utils/__init__.py
whampy/utils/tests/__init__.py
whampy-1.0.4.dist-info/LICENSE.rst
whampy-1.0.4.dist-info/METADATA
whampy-1.0.4.dist-info/WHEEL
whampy-1.0.4.dist-info/top_level.txt
whampy-1.0.4.dist-info/RECORD
